ai_api_unified/__init__.py
ai_api_unified/__version__.py
ai_api_unified/ai_base.py
ai_api_unified/ai_factory.py
ai_api_unified/completions/__init__.py
ai_api_unified/completions/ai_bedrock_completions.py
ai_api_unified/completions/ai_openai_completions.py
ai_api_unified/embeddings/__init__.py
ai_api_unified/embeddings/ai_openai_embeddings.py
ai_api_unified/embeddings/ai_titan_embeddings.py
ai_api_unified/util/__init__.py
ai_api_unified/util/env_settings.py
ai_api_unified-0.1.6.dist-info/LICENSE
ai_api_unified-0.1.6.dist-info/METADATA
ai_api_unified-0.1.6.dist-info/WHEEL
ai_api_unified-0.1.6.dist-info/RECORD
