Metadata-Version: 2.3
Name: ai_api_unified
Version: 0.1.6
Summary: Unified access layer for completion and embedding services
License: MIT
Keywords: llm,openai,bedrock,embeddings,completion,api
Author: Dave Thomas
Author-email: davidcthomas@gmail.com
Requires-Python: >=3.11,<3.13
Classifier: License :: OSI Approved :: MIT License
Classifier: Programming Language :: Python :: 3
Classifier: Programming Language :: Python :: 3.11
Classifier: Programming Language :: Python :: 3.12
Classifier: Programming Language :: Python :: 3 :: Only
Classifier: Programming Language :: Python :: 3.9
Requires-Dist: boto3 (>=1.34.0,<2.0.0)
Requires-Dist: httpx (>=0.27.0,<0.28.0)
Requires-Dist: openai (>=1.25.0,<2.0.0)
Requires-Dist: pandas (>=2.2.0,<3.0.0)
Requires-Dist: pydantic (>=2,<3)
Requires-Dist: pydantic-settings (>=2,<3)
